anvage/__init__.py
anvage/__main__.py
anvage/arguments.py
anvage/dbfasta2CdsSeq.py
anvage/flankingSequences.py
anvage/objets.py
anvage/selectAnnotatedVariants.py
anvage/synonymous.py
anvage-0.1.1.dist-info/LICENSE
anvage-0.1.1.dist-info/METADATA
anvage-0.1.1.dist-info/WHEEL
anvage-0.1.1.dist-info/entry_points.txt
anvage-0.1.1.dist-info/top_level.txt
anvage-0.1.1.dist-info/RECORD
